setup.py
BingDunDun.egg-info/PKG-INFO
BingDunDun.egg-info/SOURCES.txt
BingDunDun.egg-info/dependency_links.txt
BingDunDun.egg-info/top_level.txt
upload/__init__.py
upload/bingdundun.py