Metadata-Version: 2.1
Name: BingDunDun
Version: 2.0.0
Summary: 这是一个用海龟画图画出冰墩墩的程序代码
Home-page: UNKNOWN
Author: Eno
Author-email: 
License: UNKNOWN
Platform: UNKNOWN
